{
    "name": "AVAX-USDT",
    "feeds": [
        {
            "name": "bybit-wss-AVAX-USDT",
            "definition": {
                "type": "wss",
                "provider": "bybit",
                "base": "AVAX",
                "quote": "USDT"
            }
        },
        {
            "name": "binance-wss-AVAX-USDT",
            "definition": {
                "type": "wss",
                "provider": "binance",
                "base": "AVAX",
                "quote": "USDT"
            }
        },
        {
            "name": "kucoin-wss-AVAX-USDT",
            "definition": {
                "type": "wss",
                "provider": "kucoin",
                "base": "AVAX",
                "quote": "USDT"
            }
        },
        {
            "name": "crypto-wss-AVAX-USDT",
            "definition": {
                "type": "wss",
                "provider": "crypto",
                "base": "AVAX",
                "quote": "USDT"
            }
        },
        {
            "name": "btse-wss-AVAX-USDT",
            "definition": {
                "type": "wss",
                "provider": "btse",
                "base": "AVAX",
                "quote": "USDT"
            }
        },
        {
            "name": "coinbase-wss-AVAX-USDT",
            "definition": {
                "type": "wss",
                "provider": "coinbase",
                "base": "AVAX",
                "quote": "USDT"
            }
        },
        {
            "name": "gateio-wss-AVAX-USDT",
            "definition": {
                "type": "wss",
                "provider": "gateio",
                "base": "AVAX",
                "quote": "USDT"
            }
        },
        {
            "name": "coinex-wss-AVAX-USDT",
            "definition": {
                "type": "wss",
                "provider": "coinex",
                "base": "AVAX",
                "quote": "USDT"
            }
        },
        {
            "name": "lbank-wss-AVAX-USDT",
            "definition": {
                "type": "wss",
                "provider": "lbank",
                "base": "AVAX",
                "quote": "USDT"
            }
        },
        {
            "name": "bitget-wss-AVAX-USDT",
            "definition": {
                "type": "wss",
                "provider": "bitget",
                "base": "AVAX",
                "quote": "USDT"
            }
        },
        {
            "name": "huobi-wss-AVAX-USDT",
            "definition": {
                "type": "wss",
                "provider": "huobi",
                "base": "AVAX",
                "quote": "USDT"
            }
        },
        {
            "name": "okx-wss-AVAX-USDT",
            "definition": {
                "type": "wss",
                "provider": "okx",
                "base": "AVAX",
                "quote": "USDT"
            }
        },
        {
            "name": "kraken-wss-AVAX-USDT",
            "definition": {
                "type": "wss",
                "provider": "kraken",
                "base": "AVAX",
                "quote": "USDT"
            }
        },
        {
            "name": "bingx-wss-AVAX-USDT",
            "definition": {
                "type": "wss",
                "provider": "bingx",
                "base": "AVAX",
                "quote": "USDT"
            }
        },
        {
            "name": "bitmart-wss-AVAX-USDT",
            "definition": {
                "type": "wss",
                "provider": "bitmart",
                "base": "AVAX",
                "quote": "USDT"
            }
        },
        {
            "name": "xt-wss-AVAX-USDT",
            "definition": {
                "type": "wss",
                "provider": "xt",
                "base": "AVAX",
                "quote": "USDT"
            }
        }
    ],
    "fetchInterval": 2000,
    "aggregateInterval": 3000,
    "submitInterval": 15000
}