{
    "adapterHash": "0x3e3562ce40f6914eb529d6891f70d2367a5c45b6c2a3efbf429e8cba9dcb2812",
    "name": "BORA-KRW",
    "decimals": 8,
    "feeds": [
      {
        "name": "Coinone-BORA-KRW",
        "definition": {
          "url": "https://api.coinone.co.kr/public/v2/ticker_new/KRW/BORA",
          "headers": { "Content-Type": "application/json" },
          "method": "GET",
          "reducers": [
            { "function": "PARSE", "args": ["tickers"] },
            { "function": "INDEX", "args": 0 },
            { "function": "PARSE", "args": ["last"] },
            { "function": "POW10", "args": 8 },
            { "function": "ROUND" }
          ]
        }
      },
      {
        "name": "Bithumb-BORA-KRW",
        "definition": {
            "url": "https://api.bithumb.com/public/ticker/BORA_KRW",
            "headers": { "Content-Type": "application/json" },
            "method": "GET",
            "reducers": [
                { "function": "PARSE", "args": ["data", "closing_price"]},
                { "function": "POW10", "args": 8 },
                { "function": "ROUND" }
            ]
        }
      },
      {
        "name": "Upbit-BORA-KRW",
        "definition": {
            "url": "https://api.upbit.com/v1/ticker?markets=KRW-BORA",
            "headers": { "Content-Type": "application/json" },
            "method": "GET",
            "reducers": [
                { "function": "INDEX", "args": 0 },
                { "function": "PARSE", "args": ["trade_price"]},
                { "function": "POW10", "args": 8 },
                { "function": "ROUND" }
            ]
        }
      },
      {
        "name": "Korbit-BORA-KRW",
        "definition": {
            "url": "https://api.korbit.co.kr/v1/ticker/detailed?currency_pair=bora_krw",
            "headers": { "Content-Type": "application/json" },
            "method": "GET",
            "reducers": [
                { "function": "PARSE", "args": ["last"]},
                { "function": "POW10", "args": 8 },
                { "function": "ROUND" }
            ]
        }
      }
    ]
  }
  