{
    "name": "GLM-KRW",
    "fetchInterval": 2000,
    "aggregateInterval": 400,
    "submitInterval": 3600000,
    "feeds": [
        {
            "name": "upbit-wss-GLM-KRW",
            "definition": {
                "type": "wss",
                "provider": "upbit",
                "base": "GLM",
                "quote": "KRW"
            }
        },
        {
            "name": "bithumb-wss-GLM-KRW",
            "definition": {
                "type": "wss",
                "provider": "bithumb",
                "base": "GLM",
                "quote": "KRW"
            }
        },
        {
            "name": "coinone-wss-GLM-KRW",
            "definition": {
                "type": "wss",
                "provider": "coinone",
                "base": "GLM",
                "quote": "KRW"
            }
        },
        {
            "name": "gopax-wss-GLM-KRW",
            "definition": {
                "type": "wss",
                "provider": "gopax",
                "base": "GLM",
                "quote": "KRW"
            }
        }
    ]
}