{
    "name": "MATIC-KRW",
    "fetchInterval": 2000,
    "aggregateInterval": 400,
    "submitInterval": 3600000,
    "feeds": [
        {
            "name": "upbit-wss-MATIC-KRW",
            "definition": {
                "type": "wss",
                "provider": "upbit",
                "base": "MATIC",
                "quote": "KRW"
            }
        },
        {
            "name": "korbit-wss-MATIC-KRW",
            "definition": {
                "type": "wss",
                "provider": "korbit",
                "base": "MATIC",
                "quote": "KRW"
            }
        },
        {
            "name": "bithumb-wss-MATIC-KRW",
            "definition": {
                "type": "wss",
                "provider": "bithumb",
                "base": "MATIC",
                "quote": "KRW"
            }
        },
        {
            "name": "coinone-wss-MATIC-KRW",
            "definition": {
                "type": "wss",
                "provider": "coinone",
                "base": "MATIC",
                "quote": "KRW"
            }
        }
    ]
}